builder_updater/__init__.py
builder_updater/__main__.py
builder_updater/builder_info.py
builder_updater/builder_updater.py
builder_updater/cli.py
builder_updater/assets/example/example.code-workspace
builder_updater/assets/example/project_configs/common.mk
builder_updater/assets/example/project_configs/gitlab-ci-project.yml
builder_updater/assets/example/project_configs/build_configs/bc_first.mk
builder_updater/assets/example/project_configs/build_configs/bc_second.mk
builder_updater/assets/example/src/main.c
builder_updater/assets/template/.gitignore
builder_updater/assets/template/.gitlab-ci.yml
builder_updater/assets/template/makefile
builder_updater/assets/template/.vscode/c_cpp_properties.json
builder_updater/assets/template/.vscode/launch.json
builder_updater/assets/template/.vscode/settings.json
builder_updater/assets/template/.vscode/tasks.json
builder_updater/assets/template/build_scripts/builder.mk
builder_updater/assets/template/build_scripts/env_default.mk
builder_updater/assets/template/build_scripts/gitlab-ci-builder.yml
builder_updater/assets/template/build_scripts/global.mk
builder_updater/assets/template/build_scripts/bin_header/bin_header.c
builder_updater/assets/template/build_scripts/bin_header/bin_header.h
builder_updater/assets/template/build_scripts/crc_soft/crc_soft.c
builder_updater/assets/template/build_scripts/crc_soft/crc_soft.h
builder_updater/assets/template/build_scripts/post_build/gcc_map_parser.py
builder_updater/assets/template/build_scripts/post_build/modify_header.py
builder_updater/assets/template/project_configs/common.mk
builder_updater/assets/template/project_configs/gitlab-ci-project.yml
builder_updater/assets/template/project_configs/build_configs/bc_release.mk
builder_updater-0.1.0.dist-info/licenses/LICENSE
builder_updater-0.1.0.dist-info/METADATA
builder_updater-0.1.0.dist-info/WHEEL
builder_updater-0.1.0.dist-info/entry_points.txt
builder_updater-0.1.0.dist-info/top_level.txt
builder_updater-0.1.0.dist-info/RECORD
