Metadata-Version: 2.4
Name: builder-updater
Version: 0.1.0
Summary: C/C++ project builder updater
License-Expression: MIT
Project-URL: Homepage, https://gitlab.com/karma_electronics/desktop/builder_updater
Project-URL: Repository, https://gitlab.com/karma_electronics/desktop/builder_updater.git
Requires-Python: >=3.6
License-File: LICENSE
Dynamic: license-file
